Workbook

Sheet Rent_Data
A1: Listing_ID | B1: Source | C1: Locality | D1: Sub_Region | E1: Locality_Tier | F1: Society_Name | G1: Rent | H1: BHK | I1: Bathroom | J1: Floor | K1: Total Floors | L1: Carpet_Area_SqFt | M1: Furnishing | N1: Tenant_Type | O1: Property_Type | P1: Property_Age_Category | Q1: Property_Age_Years | R1: Posted_Date | S1: Rent_Per_SqFt | T1: Rent_Annual | U1: Rent_Band | V1: Area_Band | W1: Rate_Quality_Flag | X1: Absolute_Price_Flag | Y1: Rate_Ceiling_Flag | Z1: Data_Quality_Flag
A2: LST-001 | B2: 99acres | C2: Andheri East | D2: =VLOOKUP(C2,Locality_Reference!A:C,2,) -> Western Line | E2: =VLOOKUP(C2,Locality_Reference!A:C,3,) -> Mid Suburb | F2: Pump House Society | G2: 48000 | H2: 1 | I2: 2 | J2: 3 | K2: 7 | L2: 450 | M2: Furnished | N2: Family Only | O2: Apartment | P2: 10+ Years | Q2: =IF(P2="20+ Years","20",IF(P2="15-20 Years","17.5",IF(P2="10+ Years","10",IF(P2="5-10 Years","7.5",IF(P2="1-5 Years","3",IF(P2="0-1 Year","1","")))))) -> 10 | R2: 46193 | S2: =G2/L2 -> 106.66667 | T2: =G2*12 -> 576000 | U2: =IF(G2<=30000,"Budget",IF(G2<=60000,"Mid",IF(G2<=100000,"Premium","Luxury"))) -> Mid | V2: =IF(L2<=500,"Compact",IF(L2<=800,"Medium",IF(L2<=1200,"Large","Spacious"))) -> Compact | W2: =IF(S2 < VLOOKUP(E2, Locality_Tier_Benchmarks!A:B, 2, FALSE) * 0.7, "Below Tier Range", "Normal") -> Normal | X2: =IF(G2<7000,"Below Absolute Floor","Normal") -> Normal | Y2: =IF(S2>500,"Possible Typo - Check Zero","Normal") -> Normal | Z2: =IF(OR(W2<>"Normal",X2<>"Normal",Y2<>"Normal"),"Review","Pass") -> Pass
A3: LST-002 | B3: 99acres | C3: Andheri West | D3: =VLOOKUP(C3,Locality_Reference!A:C,2,) -> Western Line | E3: =VLOOKUP(C3,Locality_Reference!A:C,3,) -> Mid Suburb | F3: Arena Apartment | G3: 55000 | H3: 1 | I3: 2 | J3: 6 | K3: 7 | L3: 570 | M3: Furnished | N3: All | O3: Apartment | P3: 10+ Years | Q3: =IF(P3="20+ Years","20",IF(P3="15-20 Years","17.5",IF(P3="10+ Years","10",IF(P3="5-10 Years","7.5",IF(P3="1-5 Years","3",IF(P3="0-1 Year","1","")))))) -> 10 | R3: 46137 | S3: =G3/L3 -> 96.491228 | T3: =G3*12 -> 660000 | U3: =IF(G3<=30000,"Budget",IF(G3<=60000,"Mid",IF(G3<=100000,"Premium","Luxury"))) -> Mid | V3: =IF(L3<=500,"Compact",IF(L3<=800,"Medium",IF(L3<=1200,"Large","Spacious"))) -> Medium | W3: =IF(S3 < VLOOKUP(E3, Locality_Tier_Benchmarks!A:B, 2, FALSE) * 0.7, "Below Tier Range", "Normal") -> Normal | X3: =IF(G3<7000,"Below Absolute Floor","Normal") -> Normal | Y3: =IF(S3>500,"Possible Typo - Check Zero","Normal") -> Normal | Z3: =IF(OR(W3<>"Normal",X3<>"Normal",Y3<>"Normal"),"Review","Pass") -> Pass
A4: LST-003 | B4: 99acres | C4: Andheri East | D4: =VLOOKUP(C4,Locality_Reference!A:C,2,) -> Western Line | E4: =VLOOKUP(C4,Locality_Reference!A:C,3,) -> Mid Suburb | F4: Charat Singh Colony | G4: 90000 | H4: 2 | I4: 2 | J4: 3 | K4: 12 | L4: 700 | M4: Furnished | N4: All | O4: Apartment | P4: 1-5 Years | Q4: =IF(P4="20+ Years","20",IF(P4="15-20 Years","17.5",IF(P4="10+ Years","10",IF(P4="5-10 Years","7.5",IF(P4="1-5 Years","3",IF(P4="0-1 Year","1","")))))) -> 3 | R4: 46177 | S4: =G4/L4 -> 128.57143 | T4: =G4*12 -> 1080000 | U4: =IF(G4<=30000,"Budget",IF(G4<=60000,"Mid",IF(G4<=100000,"Premium","Luxury"))) -> Premium | V4: =IF(L4<=500,"Compact",IF(L4<=800,"Medium",IF(L4<=1200,"Large","Spacious"))) -> Medium | W4: =IF(S4 < VLOOKUP(E4, Locality_Tier_Benchmarks!A:B, 2, FALSE) * 0.7, "Below Tier Range", "Normal") -> Normal | X4: =IF(G4<7000,"Below Absolute Floor","Normal") -> Normal | Y4: =IF(S4>500,"Possible Typo - Check Zero","Normal") -> Normal | Z4: =IF(OR(W4<>"Normal",X4<>"Normal",Y4<>"Normal"),"Review","Pass") -> Pass
A5: LST-004 | B5: 99acres | C5: Andheri East | D5: =VLOOKUP(C5,Locality_Reference!A:C,2,) -> Western Line | E5: =VLOOKUP(C5,Locality_Reference!A:C,3,) -> Mid Suburb | F5: Lodha Eternis | G5: 77999 | H5: 2 | I5: 2 | J5: 6 | K5: 9 | L5: 642 | M5: Unfurnished | N5: All | O5: Apartment | P5: Unknown | Q5: =IF(P5="20+ Years","20",IF(P5="15-20 Years","17.5",IF(P5="10+ Years","10",IF(P5="5-10 Years","7.5",IF(P5="1-5 Years","3",IF(P5="0-1 Year","1","")))))) | R5: 46182 | S5: =G5/L5 -> 121.49377 | T5: =G5*12 -> 935988 | U5: =IF(G5<=30000,"Budget",IF(G5<=60000,"Mid",IF(G5<=100000,"Premium","Luxury"))) -> Premium | V5: =IF(L5<=500,"Compact",IF(L5<=800,"Medium",IF(L5<=1200,"Large","Spacious"))) -> Medium | W5: =IF(S5 < VLOOKUP(E5, Locality_Tier_Benchmarks!A:B, 2, FALSE) * 0.7, "Below Tier Range", "Normal") -> Normal | X5: =IF(G5<7000,"Below Absolute Floor","Normal") -> Normal | Y5: =IF(S5>500,"Possible Typo - Check Zero","Normal") -> Normal | Z5: =IF(OR(W5<>"Normal",X5<>"Normal",Y5<>"Normal"),"Review","Pass") -> Pass
A6: LST-005 | B6: 99acres | C6: Andheri West | D6: =VLOOKUP(C6,Locality_Reference!A:C,2,) -> Western Line | E6: =VLOOKUP(C6,Locality_Reference!A:C,3,) -> Mid Suburb | F6: Runwal Elegante | G6: 250000 | H6: 3 | I6: 4 | J6: 15 | K6: 33 | L6: 1318 | M6: Semi-Furnished | N6: Family Only | O6: Apartment | P6: Unknown | Q6: =IF(P6="20+ Years","20",IF(P6="15-20 Years","17.5",IF(P6="10+ Years","10",IF(P6="5-10 Years","7.5",IF(P6="1-5 Years","3",IF(P6="0-1 Year","1","")))))) | R6: 46193 | S6: =G6/L6 -> 189.68134 | T6: =G6*12 -> 3000000 | U6: =IF(G6<=30000,"Budget",IF(G6<=60000,"Mid",IF(G6<=100000,"Premium","Luxury"))) -> Luxury | V6: =IF(L6<=500,"Compact",IF(L6<=800,"Medium",IF(L6<=1200,"Large","Spacious"))) -> Spacious | W6: =IF(S6 < VLOOKUP(E6, Locality_Tier_Benchmarks!A:B, 2, FALSE) * 0.7, "Below Tier Range", "Normal") -> Normal | X6: =IF(G6<7000,"Below Absolute Floor","Normal") -> Normal | Y6: =IF(S6>500,"Possible Typo - Check Zero","Normal") -> Normal | Z6: =IF(OR(W6<>"Normal",X6<>"Normal",Y6<>"Normal"),"Review","Pass") -> Pass
A7: LST-006 | B7: 99acres | C7: Andheri East | D7: =VLOOKUP(C7,Locality_Reference!A:C,2,) -> Western Line | E7: =VLOOKUP(C7,Locality_Reference!A:C,3,) -> Mid Suburb | F7: L&T | G7: 82000 | H7: 2 | I7: 2 | J7: 2 | K7: 26 | L7: 635 | M7: Furnished | N7: All | O7: Apartment | P7: 1-5 Years | Q7: =IF(P7="20+ Years","20",IF(P7="15-20 Years","17.5",IF(P7="10+ Years","10",IF(P7="5-10 Years","7.5",IF(P7="1-5 Years","3",IF(P7="0-1 Year","1","")))))) -> 3 | R7: 46167 | S7: =G7/L7 -> 129.13386 | T7: =G7*12 -> 984000 | U7: =IF(G7<=30000,"Budget",IF(G7<=60000,"Mid",IF(G7<=100000,"Premium","Luxury"))) -> Premium | V7: =IF(L7<=500,"Compact",IF(L7<=800,"Medium",IF(L7<=1200,"Large","Spacious"))) -> Medium | W7: =IF(S7 < VLOOKUP(E7, Locality_Tier_Benchmarks!A:B, 2, FALSE) * 0.7, "Below Tier Range", "Normal") -> Normal | X7: =IF(G7<7000,"Below Absolute Floor","Normal") -> Normal | Y7: =IF(S7>500,"Possible Typo - Check Zero","Normal") -> Normal | Z7: =IF(OR(W7<>"Normal",X7<>"Normal",Y7<>"Normal"),"Review","Pass") -> Pass
A8: LST-007 | B8: 99acres | C8: Andheri West | D8: =VLOOKUP(C8,Locality_Reference!A:C,2,) -> Western Line | E8: =VLOOKUP(C8,Locality_Reference!A:C,3,) -> Mid Suburb | F8: Kabra Metro One | G8: 155000 | H8: 3 | I8: 3 | J8: 11 | K8: 21 | L8: 1250 | M8: Semi-Furnished | N8: All | O8: Apartment | P8: Unknown | Q8: =IF(P8="20+ Years","20",IF(P8="15-20 Years","17.5",IF(P8="10+ Years","10",IF(P8="5-10 Years","7.5",IF(P8="1-5 Years","3",IF(P8="0-1 Year","1","")))))) | R8: 46193 | S8: =G8/L8 -> 124 | T8: =G8*12 -> 1860000 | U8: =IF(G8<=30000,"Budget",IF(G8<=60000,"Mid",IF(G8<=100000,"Premium","Luxury"))) -> Luxury | V8: =IF(L8<=500,"Compact",IF(L8<=800,"Medium",IF(L8<=1200,"Large","Spacious"))) -> Spacious | W8: =IF(S8 < VLOOKUP(E8, Locality_Tier_Benchmarks!A:B, 2, FALSE) * 0.7, "Below Tier Range", "Normal") -> Normal | X8: =IF(G8<7000,"Below Absolute Floor","Normal") -> Normal | Y8: =IF(S8>500,"Possible Typo - Check Zero","Normal") -> Normal | Z8: =IF(OR(W8<>"Normal",X8<>"Normal",Y8<>"Normal"),"Review","Pass") -> Pass
A9: LST-008 | B9: 99acres | C9: Andheri West | D9: =VLOOKUP(C9,Locality_Reference!A:C,2,) -> Western Line | E9: =VLOOKUP(C9,Locality_Reference!A:C,3,) -> Mid Suburb | F9: Broklyn Hill | G9: 130000 | H9: 3 | I9: 3 | J9: 8 | K9: 12 | L9: 1100 | M9: Furnished | N9: All | O9: Apartment | P9: 10+ Years | Q9: =IF(P9="20+ Years","20",IF(P9="15-20 Years","17.5",IF(P9="10+ Years","10",IF(P9="5-10 Years","7.5",IF(P9="1-5 Years","3",IF(P9="0-1 Year","1","")))))) -> 10 | R9: 46146 | S9: =G9/L9 -> 118.18182 | T9: =G9*12 -> 1560000 | U9: =IF(G9<=30000,"Budget",IF(G9<=60000,"Mid",IF(G9<=100000,"Premium","Luxury"))) -> Luxury | V9: =IF(L9<=500,"Compact",IF(L9<=800,"Medium",IF(L9<=1200,"Large","Spacious"))) -> Large | W9: =IF(S9 < VLOOKUP(E9, Locality_Tier_Benchmarks!A:B, 2, FALSE) * 0.7, "Below Tier Range", "Normal") -> Normal | X9: =IF(G9<7000,"Below Absolute Floor","Normal") -> Normal | Y9: =IF(S9>500,"Possible Typo - Check Zero","Normal") -> Normal | Z9: =IF(OR(W9<>"Normal",X9<>"Normal",Y9<>"Normal"),"Review","Pass") -> Pass
A10: LST-009 | B10: 99acres | C10: Andheri West | D10: =VLOOKUP(C10,Locality_Reference!A:C,2,) -> Western Line | E10: =VLOOKUP(C10,Locality_Reference!A:C,3,) -> Mid Suburb | F10: Transcon Triumph | G10: 115000 | H10: 2 | I10: 2 | J10: 20 | K10: 35 | L10: 660 | M10: Semi-Furnished | N10: Family Only | O10: Apartment | P10: Unknown | Q10: =IF(P10="20+ Years","20",IF(P10="15-20 Years","17.5",IF(P10="10+ Years","10",IF(P10="5-10 Years","7.5",IF(P10="1-5 Years","3",IF(P10="0-1 Year","1","")))))) | R10: 46184 | S10: =G10/L10 -> 174.24242 | T10: =G10*12 -> 1380000 | U10: =IF(G10<=30000,"Budget",IF(G10<=60000,"Mid",IF(G10<=100000,"Premium","Luxury"))) -> Luxury | V10: =IF(L10<=500,"Compact",IF(L10<=800,"Medium",IF(L10<=1200,"Large","Spacious"))) -> Medium | W10: =IF(S10 < VLOOKUP(E10, Locality_Tier_Benchmarks!A:B, 2, FALSE) * 0.7, "Below Tier Range", "Normal") -> Normal | X10: =IF(G10<7000,"Below Absolute Floor","Normal") -> Normal | Y10: =IF(S10>500,"Possible Typo - Check Zero","Normal") -> Normal | Z10: =IF(OR(W10<>"Normal",X10<>"Normal",Y10<>"Normal"),"Review","Pass") -> Pass
A11: LST-010 | B11: 99acres | C11: Andheri West | D11: =VLOOKUP(C11,Locality_Reference!A:C,2,) -> Western Line | E11: =VLOOKUP(C11,Locality_Reference!A:C,3,) -> Mid Suburb | F11: Legend Apartment | G11: 70000 | H11: 2 | I11: 2 | J11: 3 | K11: 7 | L11: 720 | M11: Semi-Furnished | N11: Family Only | O11: Apartment | P11: 10+ Years | Q11: =IF(P11="20+ Years","20",IF(P11="15-20 Years","17.5",IF(P11="10+ Years","10",IF(P11="5-10 Years","7.5",IF(P11="1-5 Years","3",IF(P11="0-1 Year","1","")))))) -> 10 | R11: 46162 | S11: =G11/L11 -> 97.222222 | T11: =G11*12 -> 840000 | U11: =IF(G11<=30000,"Budget",IF(G11<=60000,"Mid",IF(G11<=100000,"Premium","Luxury"))) -> Premium | V11: =IF(L11<=500,"Compact",IF(L11<=800,"Medium",IF(L11<=1200,"Large","Spacious"))) -> Medium | W11: =IF(S11 < VLOOKUP(E11, Locality_Tier_Benchmarks!A:B, 2, FALSE) * 0.7, "Below Tier Range", "Normal") -> Normal | X11: =IF(G11<7000,"Below Absolute Floor","Normal") -> Normal | Y11: =IF(S11>500,"Possible Typo - Check Zero","Normal") -> Normal | Z11: =IF(OR(W11<>"Normal",X11<>"Normal",Y11<>"Normal"),"Review","Pass") -> Pass
A12: LST-011 | B12: 99acres | C12: Andheri East | D12: =VLOOKUP(C12,Locality_Reference!A:C,2,) -> Western Line | E12: =VLOOKUP(C12,Locality_Reference!A:C,3,) -> Mid Suburb | F12: Kalpataru Vivant | G12: 75000 | H12: 2 | I12: 2 | J12: 11 | K12: 22 | L12: 618 | M12: Semi-Furnished | N12: All | O12: Apartment | P12: Unknown | Q12: =IF(P12="20+ Years","20",IF(P12="15-20 Years","17.5",IF(P12="10+ Years","10",IF(P12="5-10 Years","7.5",IF(P12="1-5 Years","3",IF(P12="0-1 Year","1","")))))) | R12: 46192 | S12: =G12/L12 -> 121.35922 | T12: =G12*12 -> 900000 | U12: =IF(G12<=30000,"Budget",IF(G12<=60000,"Mid",IF(G12<=100000,"Premium","Luxury"))) -> Premium | V12: =IF(L12<=500,"Compact",IF(L12<=800,"Medium",IF(L12<=1200,"Large","Spacious"))) -> Medium | W12: =IF(S12 < VLOOKUP(E12, Locality_Tier_Benchmarks!A:B, 2, FALSE) * 0.7, "Below Tier Range", "Normal") -> Normal | X12: =IF(G12<7000,"Below Absolute Floor","Normal") -> Normal | Y12: =IF(S12>500,"Possible Typo - Check Zero","Normal") -> Normal | Z12: =IF(OR(W12<>"Normal",X12<>"Normal",Y12<>"Normal"),"Review","Pass") -> Pass
A13: LST-012 | B13: 99acres | C13: Andheri East | D13: =VLOOKUP(C13,Locality_Reference!A:C,2,) -> Western Line | E13: =VLOOKUP(C13,Locality_Reference!A:C,3,) -> Mid Suburb | F13: Mahindra Vivante | G13: 125000 | H13: 3 | I13: 3 | J13: 9 | K13: 12 | L13: 1100 | M13: Semi-Furnished | N13: Family Only | O13: Apartment | P13: Unknown | Q13: =IF(P13="20+ Years","20",IF(P13="15-20 Years","17.5",IF(P13="10+ Years","10",IF(P13="5-10 Years","7.5",IF(P13="1-5 Years","3",IF(P13="0-1 Year","1","")))))) | R13: 46184 | S13: =G13/L13 -> 113.63636 | T13: =G13*12 -> 1500000 | U13: =IF(G13<=30000,"Budget",IF(G13<=60000,"Mid",IF(G13<=100000,"Premium","Luxury"))) -> Luxury | V13: =IF(L13<=500,"Compact",IF(L13<=800,"Medium",IF(L13<=1200,"Large","Spacious"))) -> Large | W13: =IF(S13 < VLOOKUP(E13, Locality_Tier_Benchmarks!A:B, 2, FALSE) * 0.7, "Below Tier Range", "Normal") -> Normal | X13: =IF(G13<7000,"Below Absolute Floor","Normal") -> Normal | Y13: =IF(S13>500,"Possible Typo - Check Zero","Normal") -> Normal | Z13: =IF(OR(W13<>"Normal",X13<>"Normal",Y13<>"Normal"),"Review","Pass") -> Pass
... A1156: LST-1155 | B1156: 99acres | C1156: Marol | D1156: =VLOOKUP(C1156,Locality_Reference!A:C,2,) -> Western Line | E1156: =VLOOKUP(C1156,Locality_Reference!A:C,3,) -> Mid Suburb | F1156: Sheth Vasant Oasis | G1156: 115000 | H1156: 3 | I1156: 2 | J1156: 3 | K1156: 22 | L1156: 900 | M1156: Furnished | N1156: All | O1156: Apartment | P1156: 1-5 Years | Q1156: =IF(P1156="20+ Years","20",IF(P1156="15-20 Years","17.5",IF(P1156="10+ Years","10",IF(P1156="5-10 Years","7.5",IF(P1156="1-5 Years","3",IF(P1156="0-1 Year","1","")))))) -> 3 | R1156: 46151 | S1156: =G1156/L1156 -> 127.77778 | T1156: =G1156*12 -> 1380000 | U1156: =IF(G1156<=30000,"Budget",IF(G1156<=60000,"Mid",IF(G1156<=100000,"Premium","Luxury"))) -> Luxury | V1156: =IF(L1156<=500,"Compact",IF(L1156<=800,"Medium",IF(L1156<=1200,"Large","Spacious"))) -> Large | W1156: =IF(S1156 < VLOOKUP(E1156, Locality_Tier_Benchmarks!A:B, 2, FALSE) * 0.7, "Below Tier Range", "Normal") -> Normal | X1156: =IF(G1156<7000,"Below Absolute Floor","Normal") -> Normal | Y1156: =IF(S1156>500,"Possible Typo - Check Zero","Normal") -> Normal | Z1156: =IF(OR(W1156<>"Normal",X1156<>"Normal",Y1156<>"Normal"),"Review","Pass") -> Pass

Sheet Locality_Reference
A1: Locality | B1: Sub_Region | C1: Locality_Tier
A2: Churchgate | B2: Western Line | C2: Premium/South
A3: Marine Lines | B3: Western Line | C3: Premium/South
A4: Charni Road | B4: Western Line | C4: Premium/South
A5: Grant Road | B5: Western Line | C5: Premium/South
A6: Mumbai Central | B6: Western Line | C6: Premium/South
A7: Mahalaxmi | B7: Western Line | C7: Premium/South
A8: Lower Parel East | B8: Western Line | C8: Premium/South
A9: Lower Parel West | B9: Western Line | C9: Premium/South
A10: Prabhadevi | B10: Western Line | C10: Premium/South
A11: Dadar East | B11: Western Line | C11: Premium/South
A12: Dadar West | B12: Western Line | C12: Premium/South
... A92: Marol | B92: Western Line | C92: Mid Suburb

Sheet Locality_Tier_Benchmarks
A1: Locality_Tier | B1: Min_Rent_PerSqFt | C1: Max_Rent_PerSqFt
A2: Outer Periphery | B2: 8 | C2: 15
A3: Far Suburb | B3: 15 | C3: 25
A4: Navi Mumbai | B4: 25 | C4: 50
A5: Mid Suburb | B5: 50 | C5: 120
A6: Premium Suburb | B6: 80 | C6: 150
A7: Premium/South | B7: 100 | C7: 400

Sheet Income_Benchmarks
A1: Job_Category | B1: Monthly_Income_Median | C1: Source | D1: Source_Year
A2: IT/Software (Mumbai) | B2: 65000 | C2: SalaryBox Industry Report | D2: 2026
A3: BFSI (Mumbai) | B3: 66900 | C3: Glassdoor/6figr Mumbai BFSI Salary Data | D3: 2026
A4: General Mumbai Median | B4: 65000 | C4: SalaryBox 2026 (₹7.8 LPA ÷ 12) | D4: 2026
A5: National Median | B5: 30000 | C5: SalaryBox 2026 Industry Breakdown | D5: 2026

Sheet Data_Profile
A1: Metric | B1: Value
A2: Total Listings | B2: =ROWS(tblRentListings[]) -> 1155
A3: Total Columns | B3: =COLUMNS(tblRentListings[]) -> 26
A4: Total Localities | B4: =COUNTA(_xlfn.UNIQUE(tblRentListings[Locality])) -> 86
A5: Total Societies | B5: =COUNTA(_xlfn.UNIQUE(tblRentListings[Society_Name])) -> 1023
A6: Total BHK Types | B6: =COUNTA(_xlfn.UNIQUE(tblRentListings[BHK])) -> 4
A7: Total Property Types | B7: =COUNTA(_xlfn.UNIQUE(tblRentListings[Property_Type])) -> 1
A8: Total Sources | B8: =COUNTA(_xlfn.UNIQUE(tblRentListings[Source])) -> 2
A9: Total Furnishing Types | B9: =COUNTA(_xlfn.UNIQUE(tblRentListings[Furnishing])) -> 3
A10: Total Tenant Types | B10: =COUNTA(_xlfn.UNIQUE(tblRentListings[Tenant_Type])) -> 4
A11: Earliest Posted Date | B11: =MIN(tblRentListings[Posted_Date]) -> 46115
A12: Latest Posted Date | B12: =MAX(tblRentListings[Posted_Date]) -> 46204

Sheet Data_Dictionary
A1: Column Name | B1: Data Type | C1: Business Definition | D1: Category | E1: Sample Value | F1: Null Allowed? | G1: Importance | H1: Keep? | I1: Notes | J1: SQL Data Type | K1: Used in Dashboard? | L1: Business Question Answered
A2: Listing_ID | B2: String | C2: Unique identifier assigned to each rental listing | D2: Primary Key | E2: LST-001 | F2: No | G2: Critical | H2: Yes | I2: Primary key; every listing must be unique | J2: VARCHAR(20) | K2: No | L2: How many unique listings were analysed?
A3: Source | B3: String | C3: Property portal from which the listing was collected | D3: Dimension | E3: 99acres | F3: No | G3: Medium | H3: Yes | I3: Used for platform comparison | J3: VARCHAR(20) | K3: Yes | L3: Which platform has more listings?
A4: Locality | B4: String | C4: Area where the property is located | D4: Dimension | E4: Andheri East | F4: No | G4: Critical | H4: Yes | I4: Core geographic analysis field | J4: VARCHAR(100) | K4: Yes | L4: Which locality is the most expensive?
A5: Sub_Region | B5: String | C5: Mumbai region classification (Western, Central, Harbour, Navi Mumbai, etc.) | D5: Dimension | E5: Western Line | F5: No | G5: High | H5: Yes | I5: Used for regional comparisons | J5: VARCHAR(50) | K5: Yes | L5: Which Mumbai region has the highest average rent?
A6: Locality_Tier | B6: String | C6: Classification of locality (Premium, Mid, Budget) | D6: Dimension | E6: Mid Suburb | F6: No | G6: High | H6: Yes | I6: Helps compare pricing across market segments | J6: VARCHAR(20) | K6: Yes | L6: Do premium localities command higher rents?
A7: Society_Name | B7: String | C7: Name of the residential society/building | D7: Dimension | E7: Pump House Society | F7: Yes | G7: Low | H7: Yes | I7: Mostly descriptive because most societies have only one listing | J7: VARCHAR(150) | K7: No | L7: Which societies appear most frequently?
A8: Rent | B8: Numeric | C8: Monthly rent in Indian Rupees | D8: Fact | E8: 48000 | F8: No | G8: Critical | H8: Yes | I8: Core measure used to evaluate rental pricing and derive all pricing KPIs | J8: INTEGER | K8: Yes | L8: What is the average monthly rent?
A9: BHK | B9: Smallint | C9: Number of bedrooms | D9: Dimension | E9: 1 | F9: No | G9: Critical | H9: Yes | I9: Primary property characteristic used for rental segmentation and comparison | J9: SMALLINT | K9: Yes | L9: Which BHK category has the highest demand?
A10: Bathroom | B10: Smallint | C10: Number of bathrooms | D10: Dimension | E10: 2 | F10: No | G10: High | H10: Yes | I10: Secondary pricing factor | J10: SMALLINT | K10: Optional | L10: Does an extra bathroom increase rent?
A11: Floor | B11: Smallint | C11: Floor on which the apartment is located | D11: Dimension | E11: 3 | F11: Yes | G11: High | H11: Yes | I11: Used to analyse the influence of apartment floor level on rental pricing | J11: SMALLINT | K11: Optional | L11: Does floor level influence rent?
A12: Total_Floors | B12: Smallint | C12: Total number of floors in the building | D12: Dimension | E12: 7 | F12: Yes | G12: Medium | H12: Yes | I12: Used to analyse building height and floor position | J12: SMALLINT | K12: Optional | L12: Are taller buildings associated with higher rents?
A13: Carpet_Area_SqFt | B13: Numeric | C13: Carpet area of the apartment in square feet | D13: Fact | E13: 450 | F13: No | G13: Critical | H13: Yes | I13: Primary determinant of rental pricing | J13: INTEGER | K13: Yes | L13: How does carpet area affect rent?
A14: Furnishing | B14: String | C14: Furnishing status of the apartment | D14: Dimension | E14: Furnished | F14: No | G14: Critical | H14: Yes | I14: Used to analyse furnishing premium | J14: VARCHAR(30) | K14: Yes | L14: What is the furnishing premium?
A15: Tenant_Type | B15: String | C15: Preferred tenant category | D15: Dimension | E15: Family Only | F15: Yes | G15: Medium | H15: Yes | I15: Used to analyse rental preferences | J15: VARCHAR(30) | K15: Optional | L15: Which tenant category is most common?
A16: Property_Age_Category | B16: String | C16: Categorised age of the property | D16: Dimension | E16: 10+ Years | F16: Yes | G16: Medium | H16: Yes | I16: Used for property lifecycle analysis | J16: VARCHAR(30) | K16: Optional | L16: Do newer properties command higher rents?
A17: Property_Age_Years | B17: Numeric | C17: Approximate property age in years | D17: Fact | E17: 10 | F17: Yes | G17: High | H17: Yes | I17: Enables numerical age analysis | J17: SMALLINT | K17: Optional | L17: What is the relationship between property age and rent?
A18: Posted_Date | B18: Date | C18: Date when the listing was posted | D18: Dimension | E18: 46193 | F18: No | G18: High | H18: Yes | I18: Used for market trend analysis | J18: DATE | K18: Yes | L18: How did listings change over time?
A19: Rent_Per_SqFt | B19: Numeric | C19: Monthly rent divided by carpet area | D19: Derived | E19: 106.67 | F19: No | G19: Critical | H19: No | I19: Calculated dynamically in SQL Views | K19: Yes
A20: Rent_Annual | B20: Numeric | C20: Annual rental value | D20: Derived | E20: 576000 | F20: No | G20: Medium | H20: No | I20: Calculated as Monthly Rent × 12 for annual rental valuation | K20: No
A21: Rent_Band | B21: String | C21: Rental price segment | D21: Derived | E21: Mid | F21: No | G21: High | H21: No | I21: Generated using CASE statement | K21: Yes
A22: Area_Band | B22: String | C22: Carpet area category | D22: Derived | E22: Compact | F22: No | G22: Medium | H22: No | I22: Used for segmentation | K22: Yes
A23: Rate_Quality_Flag | B23: String | C23: Rental rate quality classification | D23: Derived | E23: Normal | F23: No | G23: Medium | H23: No | I23: Generated using business rules | K23: Optional
A24: Absolute_Price_Flag | B24: String | C24: Price classification based on rent | D24: Derived | E24: Normal | F24: No | G24: Medium | H24: No | I24: Identifies whether a listing is underpriced, fairly priced, or overpriced based on market benchmarks | K24: Yes
A25: Rate_Ceiling_Flag | B25: String | C25: Indicates rate above locality threshold | D25: Derived | E25: Normal | F25: No | G25: Low | H25: No | I25: Calculated from locality benchmarks | K25: no
A26: Data_Quality_Flag | B26: String | C26: Overall record quality indicator | D26: Derived | E26: Pass | F26: No | G26: High | H26: No | I26: Overall quality status assigned after applying predefined data validation rules | K26: Yes

Sheet Business_Glossary
A1: Term | B1: Meaning
A2: BHK | B2: Bedroom, Hall, Kitchen
A3: Carpet Area | B3: Usable floor area inside the apartment
A4: Rent Per SqFt | B4: Monthly rent divided by carpet area
A5: Furnishing Premium | B5: Additional rent attributable to furnishing status
A6: MRVI | B6: Mumbai Rental Value Index (our custom metric)
A7: Affordability Ratio | B7: Rent divided by assumed monthly salary
